MANIFEST.in
README.md
pyproject.toml
setup.py
amuse_mesa_r15140.egg-info/PKG-INFO
amuse_mesa_r15140.egg-info/SOURCES.txt
amuse_mesa_r15140.egg-info/dependency_links.txt
amuse_mesa_r15140.egg-info/requires.txt
amuse_mesa_r15140.egg-info/top_level.txt
src/amuse/community/mesa_r15140/.gitignore
src/amuse/community/mesa_r15140/Makefile
src/amuse/community/mesa_r15140/_version.py
src/amuse/community/mesa_r15140/download.py
src/amuse/community/mesa_r15140/interface.f90
src/amuse/community/mesa_r15140/interface.py
src/amuse/community/mesa_r15140/mesa_interface.f90
src/amuse/community/mesa_r15140/patch_files.py
src/amuse/community/mesa_r15140/run_star_extras.f90
src/amuse/community/mesa_r15140/examples/__init__.py
src/amuse/community/mesa_r15140/examples/basic.py
src/amuse/community/mesa_r15140/examples/basic2.py
src/amuse/community/mesa_r15140/examples/controls.py
src/amuse/community/mesa_r15140/examples/gyre.in
src/amuse/community/mesa_r15140/examples/gyre.py
src/amuse/community/mesa_r15140/examples/inlist
src/amuse/community/mesa_r15140/examples/inlist.py
src/amuse/community/mesa_r15140/examples/multi.py
src/amuse/community/mesa_r15140/examples/new_model.py
src/amuse/community/mesa_r15140/examples/photo_load.py
src/amuse/community/mesa_r15140/examples/plot.py
src/amuse/community/mesa_r15140/examples/prems.py
src/amuse/community/mesa_r15140/examples/purehe.py
src/amuse/community/mesa_r15140/examples/rotation.py
src/amuse/community/mesa_r15140/examples/save_and_load.py
src/amuse/community/mesa_r15140/examples/sun.py
src/amuse/community/mesa_r15140/mesa_reqs/README
src/amuse/community/mesa_r15140/patches/0001-Add-support-for-namelist-setting-from-a-string.patch
src/amuse/community/mesa_r15140/patches/0001-Dont-make-empty-output-directories.patch
src/amuse/community/mesa_r15140/patches/0001-Fix-astero-builds-when-disabled.patch
src/amuse/community/mesa_r15140/patches/0001-Get-photo-loading-working.patch
src/amuse/community/mesa_r15140/patches/0001-Patch-error-messages.patch
src/amuse/community/mesa_r15140/patches/0001-Stop-crashes-when-profile-column-name-is-bad.patch
src/amuse/community/mesa_r15140/patches/0001-declare-i.patch
